odoo/addons/shopinvader_locomotive_sale_profile/README.rst
odoo/addons/shopinvader_locomotive_sale_profile/__init__.py
odoo/addons/shopinvader_locomotive_sale_profile/__manifest__.py
odoo/addons/shopinvader_locomotive_sale_profile/components/__init__.py
odoo/addons/shopinvader_locomotive_sale_profile/components/shopinvader_sale_profile_listener.py
odoo/addons/shopinvader_locomotive_sale_profile/i18n/shopinvader_locomotive_sale_profile.pot
odoo/addons/shopinvader_locomotive_sale_profile/readme/CONTRIBUTORS.rst
odoo/addons/shopinvader_locomotive_sale_profile/readme/DESCRIPTION.rst
odoo/addons/shopinvader_locomotive_sale_profile/static/description/index.html
odoo/addons/shopinvader_locomotive_sale_profile/tests/__init__.py
odoo/addons/shopinvader_locomotive_sale_profile/tests/test_shopinvader_partner.py
odoo14_addon_shopinvader_locomotive_sale_profile-14.0.1.0.1.dist-info/METADATA
odoo14_addon_shopinvader_locomotive_sale_profile-14.0.1.0.1.dist-info/WHEEL
odoo14_addon_shopinvader_locomotive_sale_profile-14.0.1.0.1.dist-info/top_level.txt
odoo14_addon_shopinvader_locomotive_sale_profile-14.0.1.0.1.dist-info/RECORD
