Metadata-Version: 2.1
Name: odoo14-addon-shopinvader-locomotive-sale-profile
Version: 14.0.1.0.1
Summary: Synchronize the sale profile info to customer record on Locomotive
Home-page: https://github.com/shopinvader/odoo-shopinvader
Author: Akretion,Camptocamp
License: AGPL-3
Platform: UNKNOWN
Classifier: Programming Language :: Python
Classifier: Framework :: Odoo
Classifier: Framework :: Odoo :: 14.0
Classifier: License :: OSI Approved :: GNU Affero General Public License v3
Requires-Python: >=3.6
Requires-Dist: odoo14-addon-shopinvader-locomotive
Requires-Dist: odoo14-addon-shopinvader-sale-profile
Requires-Dist: odoo (<14.1dev,>=14.0a)
